LICENSE
README.md
organoids/__init__.py
organoids/__main__.py
organoids/utils.py
organoids/commands/48_48_checkpointv2.pth
organoids/commands/analyze.py
organoids/commands/cifarx.py
organoids/commands/evaluate.py
organoids/commands/ocr.py
organoids/commands/prune.py
organoids/commands/rank.py
organoids/commands/segment.py
organoids-1.3.2.dist-info/METADATA
organoids-1.3.2.dist-info/WHEEL
organoids-1.3.2.dist-info/entry_points.txt
organoids-1.3.2.dist-info/licenses/LICENSE
organoids-1.3.2.dist-info/RECORD
