Metadata-Version: 2.4
Name: organoids
Version: 1.3.2
Summary: A segmentation and area estimation for organoids on microscope images.
Project-URL: Homepage, https://github.com/schneiderkamplab/organoids
Project-URL: Bug Tracker, https://github.com/schneiderkamplab/organoids/issues
Author: Peter Schneider-Kamp
License-File: LICENSE
Classifier: License :: OSI Approved :: MIT License
Classifier: Operating System :: OS Independent
Classifier: Programming Language :: Python :: 3
Requires-Python: >=3.10
Requires-Dist: click
Requires-Dist: exif
Requires-Dist: labelme
Requires-Dist: opencv-python
Requires-Dist: pandas
Requires-Dist: shapely
Requires-Dist: torch
Requires-Dist: torchvision
Requires-Dist: transformers
Requires-Dist: zstandard
